{
	"backtraceGraph" : 
	{
		"commands" : 
		[
			"install",
			"install_project"
		],
		"files" : 
		[
			"third_party/googletest/googletest/CMakeLists.txt",
			"third_party/googletest/googletest/cmake/internal_utils.cmake"
		],
		"nodes" : 
		[
			{
				"file" : 0
			},
			{
				"command" : 0,
				"file" : 0,
				"line" : 97,
				"parent" : 0
			},
			{
				"command" : 0,
				"file" : 0,
				"line" : 103,
				"parent" : 0
			},
			{
				"command" : 1,
				"file" : 0,
				"line" : 151,
				"parent" : 0
			},
			{
				"command" : 0,
				"file" : 1,
				"line" : 303,
				"parent" : 3
			},
			{
				"command" : 0,
				"file" : 1,
				"line" : 306,
				"parent" : 3
			},
			{
				"command" : 0,
				"file" : 1,
				"line" : 316,
				"parent" : 3
			},
			{
				"command" : 0,
				"file" : 1,
				"line" : 316,
				"parent" : 3
			}
		]
	},
	"installers" : 
	[
		{
			"backtrace" : 1,
			"component" : "Unspecified",
			"destination" : "lib/cmake/GTest",
			"exportName" : "GTestTargets",
			"exportTargets" : 
			[
				{
					"id" : "gtest::@2da1aeaa2813d1b6ae91",
					"index" : 6
				},
				{
					"id" : "gtest_main::@2da1aeaa2813d1b6ae91",
					"index" : 9
				},
				{
					"id" : "gmock::@1fd7ba4b7f21464e3d50",
					"index" : 0
				},
				{
					"id" : "gmock_main::@1fd7ba4b7f21464e3d50",
					"index" : 3
				}
			],
			"paths" : 
			[
				"third_party/googletest/googlemock/gtest/CMakeFiles/Export/0c08b8e77dd885bfe55a19a9659d9fc1/GTestTargets.cmake"
			],
			"type" : "export"
		},
		{
			"backtrace" : 2,
			"component" : "Unspecified",
			"destination" : "lib/cmake/GTest",
			"paths" : 
			[
				"out/build/debug/third_party/googletest/googlemock/gtest/generated/GTestConfigVersion.cmake",
				"out/build/debug/third_party/googletest/googlemock/gtest/generated/GTestConfig.cmake"
			],
			"type" : "file"
		},
		{
			"backtrace" : 4,
			"component" : "Unspecified",
			"destination" : "include",
			"paths" : 
			[
				{
					"from" : "third_party/googletest/googletest/include",
					"to" : "."
				}
			],
			"type" : "directory"
		},
		{
			"backtrace" : 5,
			"component" : "Unspecified",
			"destination" : "lib",
			"paths" : 
			[
				"third_party/googletest/googlemock/gtest/gtestd.lib"
			],
			"targetId" : "gtest::@2da1aeaa2813d1b6ae91",
			"targetIndex" : 6,
			"type" : "target"
		},
		{
			"backtrace" : 5,
			"component" : "Unspecified",
			"destination" : "lib",
			"paths" : 
			[
				"third_party/googletest/googlemock/gtest/gtest_maind.lib"
			],
			"targetId" : "gtest_main::@2da1aeaa2813d1b6ae91",
			"targetIndex" : 9,
			"type" : "target"
		},
		{
			"backtrace" : 6,
			"component" : "Unspecified",
			"destination" : "lib/pkgconfig",
			"paths" : 
			[
				"out/build/debug/third_party/googletest/googlemock/gtest/generated/gtest.pc"
			],
			"type" : "file"
		},
		{
			"backtrace" : 7,
			"component" : "Unspecified",
			"destination" : "lib/pkgconfig",
			"paths" : 
			[
				"out/build/debug/third_party/googletest/googlemock/gtest/generated/gtest_main.pc"
			],
			"type" : "file"
		}
	],
	"paths" : 
	{
		"build" : "third_party/googletest/googlemock/gtest",
		"source" : "third_party/googletest/googletest"
	}
}
